lowpolify/__init__.py
lowpolify/cli.py
lowpolify/lowpolify.py
lowpolify-0.1.0.dist-info/AUTHORS.rst
lowpolify-0.1.0.dist-info/LICENSE
lowpolify-0.1.0.dist-info/METADATA
lowpolify-0.1.0.dist-info/WHEEL
lowpolify-0.1.0.dist-info/entry_points.txt
lowpolify-0.1.0.dist-info/top_level.txt
lowpolify-0.1.0.dist-info/RECORD
